{
    "fieldNumber": "34",
    "title": "TQ",
    "name": "Translation Questionnaire Request",
    "definition": " Indicates that a translation questionnaire is being submitted. ",
    "validEntries": "\n1\nst\n%20Position%20\nA%20\n%3D%20\nNo%20TQ%20attached%20\nB%20%3D%20FGB%20translations%20\nC%20\n%3D%20\nCode%20(NPA%2FNXX)%20Translation%20Routing%20Only%20\nD%20%3D%20FGD%20translations%20\nE%20\n%3D%20\nSTP%20Translation%20Changes%20\nL%20%3D%20Local%20translations%20\nM%20\n%3D%20\nLocal%20translations%20and%20Code%20Translation%20Routing%20\nS%20%3D%20SAC%20only%20\nT\n%3D%20\nFGD%20translations%20and%20SAC%20\nU%20\n%3D%20\nFGB%20translations%20and%20SAC%20\nW%20%3D%20Wireless%20translations%20\nX%20\n%3D%20\nWireless%20translations%20and%20Code%20Translation%20Routing%20\n1-9%20%3D%20\nT\nQ%20on%20file%20\n2\nnd\n%20Position%20\nN%20\n%3D%20\nNo%20Trunking%20Form%20\nX%20%3D%20\nT\nrunking%20Form%20\n(\nno%20trunk%20activity\n)\nY%20%3D%20\nT\nrunking%20Form%20\n(\ntrunk%20activity\n)",
    "count": 0,
    "validEntryNotes": " When the first position of TQ is \"A\", the ASR which has the TQ Form attached will be identified in the RPON field. \nWhen the first position of TQ is \"L\", \"M\", \"W\", \"X\" or \"C\", entries in the CC or WST, or the CC and the WST fields are required. \nWhen the first position of TQ is \"A\", \"B\", \"D\", \"S\", \"T\", \"U\", or \"1-9\", entries in the CC or WST, or the CC and the WST fields are prohibited. \nThe second position of \"X\" indicates a Trunkin g Form is provided for system requirements rather than provisioning purposes. \nWhen the ACT field is \"N\", a second position of \"N\" or \"X\" is prohibited. \n When the first position of the TQ field is \"E\", the second position of the TQ field must be an \"X\". \n When the first position of the TQ field is \"E\", the first position of the REQTYP field must be an \"L\" and the ACT field must be a \"C\". 8%3A  When the first position of the TQ field is \"C\", the first position of the REQTYP field must be an \"M\" and the ACT field must be a \"C\". ",
    "usage": "Conditional",
    "usageNotes": " Required when the first position of the REQTYP field is \"M\", the ACT field is \"N\" and the AC TI field is \"B\" or \"C\". \nOptional when the first position of the REQTYP field is \"L\" or \"M\" and the ACT field is \"C\". \nRequired when the first position of the REQTYP field is \"M\", the ACT field is \"D\" and the ACTI field is \"E\". \nOtherwise prohibited. ",
    "dataCharacteristics": "Alphanumeric",
    "fieldLength": "2",
    "examples": "\nD\nY\n1%20Y"
}