{
    "asogVersion": "50",
    "processed": "2015-07-27T16:21:24.118Z",
    "form": "ASR",
    "section": "ADMINISTRATIVE SECTION",
    "fieldNumber": "25",
    "title": "WST",
    "name": "Wireless Service Type",
    "definition": " Identifies the type of wireless service being requested. ",
    "validEntries": [
        {
            "value": "A ",
            "description": "Dial Mobile or Paging "
        },
        {
            "value": "B ",
            "description": "Manual Mobile with DA allowance "
        },
        {
            "value": "C ",
            "description": " Manual Paging "
        },
        {
            "value": "D ",
            "description": "Type Dial Live Line "
        },
        {
            "value": "E ",
            "description": "Type 1 Direct Inward Dial Trun"
        },
        {
            "value": "",
            "description": "k"
        },
        {
            "value": "F ",
            "description": "Type 2A Tandem Interconnection "
        },
        {
            "value": "G ",
            "description": "Type 2B End Office Interconnection "
        },
        {
            "value": "H ",
            "description": "Type 1 Trunk Side Message Toll "
        },
        {
            "value": "J ",
            "description": "Type 2D Direct connection to a DA Tandem "
        },
        {
            "value": "K ",
            "description": "2T Equal Access Tandem trunks "
        },
        {
            "value": "L ",
            "description": "2C E911 to a selector router "
        },
        {
            "value": "M ",
            "description": "EO 251/252  End Office trunks (with full NXX) "
        },
        {
            "value": "N ",
            "description": "AX 251/252 Auxiliary trunk with basic 911, DA, OS"
        },
        {
            "value": "",
            "description": "and IC PIC "
        },
        {
            "value": "P ",
            "description": " ME 251/252 Modified End Office "
        },
        {
            "value": "",
            "description": "("
        },
        {
            "value": "",
            "description": "Land to Mobile"
        },
        {
            "value": "",
            "description": "blocks of 100%E2%80%99s or 1000%E2%80%99s) "
        },
        {
            "value": "R ",
            "description": "TD 251/252 Tandem trun"
        },
        {
            "value": "",
            "description": "k"
        },
        {
            "value": "S ",
            "description": "TT 251/252 Transit trunk (for IC traffic) "
        },
        {
            "value": "T",
            "description": "Direct connection to an operator tandem "
        }
    ],
    "count": 23,
    "usage": "Conditional",
    "usageNotes": " Prohibited when the first position of the REQTYP field is \"S\", \"W\", \"L\", \"R\", \"V\" or \"X\". \nProhibited when the ACT field is \"D\" and the ACTI field is \"D\" or \"F\". \nOtherwise optional. ",
    "dataCharacteristics": "Alpha",
    "fieldLength": "1",
    "examples": "\nD"
}