{
    "asogVersion": "0050",
    "processed": "2015-08-10T17:34:02.997Z",
    "form": "ASR",
    "section": "CONTACT",
    "name": " Telephone Number (IMPCON)",
    "title": "TEL NO IMPCON",
    "fieldNumber": "123",
    "minimumLength": "",
    "maximumLength": "14",
    "characteristics": "Numeric",
    "usage": "Conditional",
    "definition": " Identifies the telephone number of the implementation contact. ",
    "validEntry": [],
    "validEntryNotes": [],
    "usageNotes": [
        "Required when the IMPCON field is populated   otherwise prohibited."
    ],
    "fieldNotes": [],
    "exampleNotes": []
}